rubberduck_chat/__init__.py
rubberduck_chat/configs.py
rubberduck_chat/input_handler.py
rubberduck_chat/rubberduck.py
rubberduck_chat/store.py
rubberduck_chat/utils.py
rubberduck_chat/chat_gpt/__init__.py
rubberduck_chat/chat_gpt/chat.py
rubberduck_chat/chat_gpt/credentials.py
rubberduck_chat/chat_gpt/session_store.py
rubberduck_chat/chat_gpt/setup_gpt.py
open_coder-0.5.8.dist-info/LICENSE
open_coder-0.5.8.dist-info/METADATA
open_coder-0.5.8.dist-info/WHEEL
open_coder-0.5.8.dist-info/entry_points.txt
open_coder-0.5.8.dist-info/top_level.txt
open_coder-0.5.8.dist-info/RECORD
